{"GlobalPropertiesHash":"ah/nBKVpnzkmH0PXB3Zf/xKLLEAz4MEWto0JqyECj0U=","FingerprintPatternsHash":"gq3WsqcKBUGTSNle7RKKyXRIwh7M8ccEqOqYvIzoM04=","PropertyOverridesHash":"8ZRc1sGeVrPBx4lD717BgRaQekyh78QKV9SKsdt638U=","InputHashes":["cQtyDpnDgK3SjBskdzcgOb57ra59jgTFtRFAr8kMc14=","j9THkgctJqxxYgVg4XWnoWdlegnG\u002B4dvp8\u002B1nhmJAxA=","sJ9kdnUZeBwyy4syOwJHgxKjVEMPD\u002BdUql4zaoAhDaU=","fhMI6IZ4yGSISrJQ2IhE0Aa8KoUlkwLbtkyP9XI0oe8=","5aRYHe/VUQIWxk2bhqxivPzeQ/V6PqpHTOK6yeLJ7e0=","nvPnra42\u002BfWzY8TqBBeUhlUfnM1d4lvTztGlxe\u002BEric=","EoQrPzR2IorAqq0ovO/jn\u002BJztmY2LZ0Z12Gugp8IIJE=","gKIx9W2I8\u002BeNyIm\u002BS0n/5F6U6A\u002BxL1TDLwBlcmURqkg="],"CachedAssets":{"cQtyDpnDgK3SjBskdzcgOb57ra59jgTFtRFAr8kMc14=":{"Identity":"F:\\CAPSTONE\\DailyRoutineApp\\wwwroot\\css\\site.css","SourceId":"DailyRoutineApp","SourceType":"Discovered","ContentRoot":"F:\\CAPSTONE\\DailyRoutineApp\\wwwroot\\","BasePath":"/","RelativePath":"css/site#[.{fingerprint}]?.css","AssetKind":"All","AssetMode":"All","AssetRole":"Primary","AssetMergeBehavior":null,"AssetMergeSource":"","RelatedAsset":null,"AssetTraitName":null,"AssetTraitValue":null,"Fingerprint":"awy59mh7zo","Integrity":"Fi\u002B0yYsTNcDIEtmYLCqKSU4GtdUHz1EEr6fYC84bRvI=","CopyToOutputDirectory":"Never","CopyToPublishDirectory":"PreserveNewest","OriginalItemSpec":"wwwroot\\css\\site.css","FileLength":64,"LastWriteTime":"2026-03-02T13:49:34.2995364+00:00"}},"CachedCopyCandidates":{}}